tumtum_common/caching/__init__.py
tumtum_common/caching/annotations.py
tumtum_common/caching/clients.py
tumtum_common/caching/common_formats.py
tumtum_common/caching/models.py
tumtum_common/database/__init__.py
tumtum_common/database/annotations.py
tumtum_common/database/core.py
tumtum_common/exceptions.py
tumtum_common/jwt/__init__.py
tumtum_common/jwt/annotations.py
tumtum_common/jwt/configs.py
tumtum_common/jwt/core.py
tumtum_common/jwt/models.py
tumtum_common/logging/__init__.py
tumtum_common/logging/setup.py
tumtum_common/logging/wrappers.py
tumtum_common/messaging/__init__.py
tumtum_common/messaging/consumers.py
tumtum_common/messaging/producers.py
tumtum_common/models/__init__.py
tumtum_common/models/dtos.py
tumtum_common/models/entities.py
tumtum_common/utils/__init__.py
tumtum_common/utils/annotations.py
tumtum_common/utils/enums.py
tumtum_common/utils/global_exception_handlers.py
tumtum_common-0.2.1.dist-info/METADATA
tumtum_common-0.2.1.dist-info/WHEEL
tumtum_common-0.2.1.dist-info/RECORD
