Metadata-Version: 2.3
Name: tumtum-common
Version: 0.2.1
Summary: Общий пакет для микросервисов
Author: Максим
Author-email: maksim_goncharov_2006@mail.ru
Requires-Python: >=3.13
Classifier: Programming Language :: Python :: 3
Classifier: Programming Language :: Python :: 3.13
Requires-Dist: aiokafka (>=0.12.0,<0.13.0)
Requires-Dist: fastapi (>=0.115.12,<0.116.0)
Requires-Dist: pydantic (>=2.11.5,<3.0.0)
Requires-Dist: redis (>=6.2.0,<7.0.0)
Requires-Dist: sqlalchemy (>=2.0.41,<3.0.0)
